Topsis/__init__.py
Topsis_Dishant_101917006-1.0.0.dist-info/METADATA
Topsis_Dishant_101917006-1.0.0.dist-info/WHEEL
Topsis_Dishant_101917006-1.0.0.dist-info/top_level.txt
Topsis_Dishant_101917006-1.0.0.dist-info/RECORD
