Metadata-Version: 2.1
Name: Topsis_Dishant_101917006
Version: 1.0.0
Summary: Assignment of Dishant Sethi
Home-page: 
Author: Dishant Sethi
Author-email: dishantsethi266@gmail.com
License: MIT
Platform: UNKNOWN
Classifier: License :: OSI Approved :: MIT License
Classifier: Programming Language :: Python :: 3.6
Classifier: Programming Language :: Python :: 3.7
Classifier: Programming Language :: Python :: 3.8
